simply_nwb/__init__.py
simply_nwb/simple_nwb.py
simply_nwb/util.py
simply_nwb/pipeline/__init__.py
simply_nwb/pipeline/chain.py
simply_nwb/pipeline/funcinfo.py
simply_nwb/pipeline/value_mapping.py
simply_nwb/pipeline/enrichments/__init__.py
simply_nwb/pipeline/enrichments/example.py
simply_nwb/pipeline/enrichments/saccades/__init__.py
simply_nwb/pipeline/enrichments/saccades/predict_gui.py
simply_nwb/pipeline/enrichments/saccades/predict_ml_model.py
simply_nwb/pipeline/enrichments/saccades/predicted.py
simply_nwb/pipeline/enrichments/saccades/predicted_algorithm.py
simply_nwb/pipeline/enrichments/saccades/putative.py
simply_nwb/pipeline/enrichments/saccades/drifting_grating/__init__.py
simply_nwb/pipeline/enrichments/saccades/drifting_grating/base.py
simply_nwb/pipeline/enrichments/saccades/drifting_grating/ephys.py
simply_nwb/pipeline/enrichments/saccades/drifting_grating/labjack.py
simply_nwb/pipeline/util/__init__.py
simply_nwb/pipeline/util/waves.py
simply_nwb/pipeline/util/models/__init__.py
simply_nwb/pipeline/util/models/direction_model.py
simply_nwb/pipeline/util/models/nasal_epoch_regressor.py
simply_nwb/pipeline/util/models/nasal_epoch_transformer.py
simply_nwb/pipeline/util/models/temporal_epoch_regressor.py
simply_nwb/pipeline/util/models/temporal_epoch_transformer.py
simply_nwb/pipeline/util/saccade_algo/__init__.py
simply_nwb/pipeline/util/saccade_algo/directional.py
simply_nwb/pipeline/util/saccade_algo/epochs.py
simply_nwb/pipeline/util/saccade_gui/__init__.py
simply_nwb/pipeline/util/saccade_gui/classifiers.py
simply_nwb/pipeline/util/saccade_gui/consts.py
simply_nwb/pipeline/util/saccade_gui/data_generator.py
simply_nwb/pipeline/util/saccade_gui/direction.py
simply_nwb/pipeline/util/saccade_gui/epochs.py
simply_nwb/transferring/__init__.py
simply_nwb/transferring/nwb_transfer.py
simply_nwb/transferring/filesync/__init__.py
simply_nwb/transferring/filesync/oneway.py
simply_nwb/transforms/__init__.py
simply_nwb/transforms/blackrock.py
simply_nwb-1.4.4.dist-info/LICENSE
simply_nwb-1.4.4.dist-info/METADATA
simply_nwb-1.4.4.dist-info/WHEEL
simply_nwb-1.4.4.dist-info/top_level.txt
simply_nwb-1.4.4.dist-info/RECORD
