Metadata-Version: 2.1
Name: simply_nwb
Version: 1.4.4
Summary: Common NWB use cases and simplified interface for common usage
Author: Spencer Hanson
Keywords: neuroscience,nwb,tools,science
Classifier: Programming Language :: Python :: 3
License-File: LICENSE
Requires-Dist: pynwb
Requires-Dist: nwbinspector
Requires-Dist: neo
Requires-Dist: numpy
Requires-Dist: pendulum
Requires-Dist: pandas
Requires-Dist: pyyaml
Requires-Dist: opencv-python-headless
Requires-Dist: Pillow
Requires-Dist: imageio
Requires-Dist: av
Requires-Dist: fastcrc
Requires-Dist: scipy
Requires-Dist: scikit-learn
Requires-Dist: dict-plus
Requires-Dist: spencer-funcs>=0.0.3
Requires-Dist: matplotlib
Requires-Dist: plotly
Requires-Dist: ipympl
Requires-Dist: population-analysis
